examples/__init__.py
examples/fastapi.py
examples/flask.py
examples/sample.py
fast_resource/__init__.py
fast_resource/resource.py
fast_resource/resource_cache.py
fast_resource/cache/__init__.py
fast_resource/cache/cache.py
fast_resource/cache/memcached_cache.py
fast_resource/cache/redis_cache.py
fast_resource-0.1.1.dist-info/LICENSE
fast_resource-0.1.1.dist-info/METADATA
fast_resource-0.1.1.dist-info/WHEEL
fast_resource-0.1.1.dist-info/top_level.txt
fast_resource-0.1.1.dist-info/RECORD
