Metadata-Version: 2.1
Name: fast-resource
Version: 0.1.1
Summary: fast-resource is a data transformation layer that sits between the database and the application's users, enabling quick data retrieval. It further enhances performance by caching data using Redis and Memcached.
Home-page: https://github.com/bagher/fast-resource
Author: Bagher Rokni
Author-email: bagher.rokni@gmail.com
License: LICENSE.txt
Requires-Python: >=3
License-File: LICENSE
Requires-Dist: redis
Requires-Dist: pymemcache
